LICENSE
MANIFEST.in
README.md
package.json
setup.py
multiselect_dropdown/MultiselectDropdown.py
multiselect_dropdown/__init__.py
multiselect_dropdown/_imports_.py
multiselect_dropdown/metadata.json
multiselect_dropdown/multiselect_dropdown.min.js
multiselect_dropdown/multiselect_dropdown.min.js.map
multiselect_dropdown/package-info.json
multiselect_dropdown.egg-info/PKG-INFO
multiselect_dropdown.egg-info/SOURCES.txt
multiselect_dropdown.egg-info/dependency_links.txt
multiselect_dropdown.egg-info/top_level.txt