Metadata-Version: 1.1
Name: multiselect-dropdown
Version: 0.0.1
Summary: multi select dropdown
Home-page: UNKNOWN
Author: kalimuthu periyasamy <1995kalimuthu@gmail.com>
Author-email: UNKNOWN
License: MIT
Platform: UNKNOWN
Classifier: Framework :: Dash
